gbit/__init__.py
gbit/runner_.py
gbit/var.py
gbit/bin/bash.py
gbit/bin/crontab.py
gbit/bin/find.py
gbit/bin/less.py
gbit/bin/pkexec.py
gbit-0.2.4.dist-info/entry_points.txt
gbit-0.2.4.dist-info/LICENSE
gbit-0.2.4.dist-info/WHEEL
gbit-0.2.4.dist-info/METADATA
gbit-0.2.4.dist-info/RECORD
