Metadata-Version: 2.1
Name: gbit
Version: 0.2.4
Summary: GTFOBINS in the Terminal
Author: wolf (Calvin Kimani)
Classifier: License :: OSI Approved :: GNU General Public License v3 or later (GPLv3+)
Project-URL: Home, https://github.com/wo1fbit/gbit
Project-URL: Issues, https://github.com/wo1fbit/gbit/issues
